Metadata-Version: 2.1
Name: egen111222-my-package23
Version: 1.0
Summary: Python Distribution Utilities
Home-page: https://www.python.org/sigs/distutils-sig/
Author: Greg Ward
Author-email: gward@python.net
License: UNKNOWN
Platform: UNKNOWN
